[
    {
        "query": "freight train",
        "file": "S08322.pdf",
        "relevance": 3,
        "user_name": "maia",
        "topic_num": "Maia-20"
    },
    {
        "query": "freight train",
        "file": "S18596.pdf",
        "relevance": 3,
        "user_name": "maia",
        "topic_num": "Maia-20"
    },
    {
        "query": "freight train",
        "file": "S16814.pdf",
        "relevance": 3,
        "user_name": "maia",
        "topic_num": "Maia-20"
    },
    {
        "query": "freight train",
        "file": "S20329.pdf",
        "relevance": 3,
        "user_name": "maia",
        "topic_num": "Maia-20"
    },
    {
        "query": "freight train",
        "file": "S00975.pdf",
        "relevance": 3,
        "user_name": "maia",
        "topic_num": "Maia-20"
    },
    {
        "query": "freight train",
        "file": "S18538.pdf",
        "relevance": 3,
        "user_name": "maia",
        "topic_num": "Maia-20"
    },
    {
        "query": "freight train",
        "file": "S23185.pdf",
        "relevance": 3,
        "user_name": "maia",
        "topic_num": "Maia-20"
    },
    {
        "query": "freight shipping",
        "file": "S18596.pdf",
        "relevance": 3,
        "user_name": "maia",
        "topic_num": "Maia-20"
    },
    {
        "query": "freight shipping",
        "file": "S08322.pdf",
        "relevance": 3,
        "user_name": "maia",
        "topic_num": "Maia-20"
    },
    {
        "query": "freight shipping",
        "file": "S16814.pdf",
        "relevance": 3,
        "user_name": "maia",
        "topic_num": "Maia-20"
    },
    {
        "query": "freight shipping",
        "file": "S23185.pdf",
        "relevance": 3,
        "user_name": "maia",
        "topic_num": "Maia-20"
    },
    {
        "query": "freight shipping",
        "file": "S20329.pdf",
        "relevance": 3,
        "user_name": "maia",
        "topic_num": "Maia-20"
    },
    {
        "query": "freight shipping",
        "file": "S05981.pdf",
        "relevance": 3,
        "user_name": "maia",
        "topic_num": "Maia-20"
    },
    {
        "query": "freight shipping",
        "file": "S15626.pdf",
        "relevance": 3,
        "user_name": "maia",
        "topic_num": "Maia-20"
    },
    {
        "query": "freight shipping",
        "file": "S00975.pdf",
        "relevance": 3,
        "user_name": "maia",
        "topic_num": "Maia-20"
    },
    {
        "query": "freight shipping",
        "file": "S18538.pdf",
        "relevance": 3,
        "user_name": "maia",
        "topic_num": "Maia-20"
    },
    {
        "query": "freight shipping",
        "file": "S12473.pdf",
        "relevance": 3,
        "user_name": "maia",
        "topic_num": "Maia-20"
    },
    {
        "query": "freight shipping",
        "file": "S02922.pdf",
        "relevance": 3,
        "user_name": "maia",
        "topic_num": "Maia-20"
    },
    {
        "query": "freight shipping",
        "file": "S15236.pdf",
        "relevance": 3,
        "user_name": "maia",
        "topic_num": "Maia-20"
    },
    {
        "query": "freight shipping policies",
        "file": "S00975.pdf",
        "relevance": 3,
        "user_name": "maia",
        "topic_num": "Maia-20"
    }
]